TlsProxy/__init__.py
TlsProxy/client.py
TlsProxy/config.py
TlsProxy/flags.py
TlsProxy/server.py
TlsProxy/utils.py
TlsProxys-1.0.5.dist-info/LICENSE
TlsProxys-1.0.5.dist-info/METADATA
TlsProxys-1.0.5.dist-info/WHEEL
TlsProxys-1.0.5.dist-info/entry_points.txt
TlsProxys-1.0.5.dist-info/top_level.txt
TlsProxys-1.0.5.dist-info/RECORD
