Metadata-Version: 2.1
Name: TlsProxys
Version: 1.0.5
Summary: a safe http proxy over tls
Home-page: https://www.github.com/loniceraLeo/TlsProxy
Author: github.com/loniceraLeo
License: GPL
Platform: windows
Platform: linux
Requires-Python: >=3.7.0
